{
  "teamId": "211",
  "page": 1,
  "totalPages": 52,
  "items": [
    {
      "id": 2800320,
      "leagueId": 11,
      "leagueColor": "#663333",
      "playtime": "2026/05/16 23:00",
      "leagueName": "法甲",
      "homeName": "马赛",
      "homeId": 211,
      "awayName": "雷恩",
      "awayId": 251,
      "fullscore": "",
      "halfscore": "",
      "result": "",
      "raw": [
        2800320,
        11,
        "#663333",
        "2026/05/16 23:00",
        211,
        251,
        "",
        "",
        "法甲",
        "法甲",
        "FRA D1",
        "马赛",
        "馬賽",
        "Marseille",
        "雷恩",
        "雷恩",
        "Rennes",
        0,
        0,
        "",
        "",
        "",
        "",
        "",
        1
      ]
    },
    {
      "id": 2800309,
      "leagueId": 11,
      "leagueColor": "#663333",
      "playtime": "2026/05/09 23:00",
      "leagueName": "法甲",
      "homeName": "勒阿弗尔",
      "homeId": 335,
      "awayName": "马赛",
      "awayId": 211,
      "fullscore": "",
      "halfscore": "",
      "result": "",
      "raw": [
        2800309,
        11,
        "#663333",
        "2026/05/09 23:00",
        335,
        211,
        "",
        "",
        "法甲",
        "法甲",
        "FRA D1",
        "勒阿弗尔",
        "勒哈費爾",
        "Le Havre",
        "马赛",
        "馬賽",
        "Marseille",
        0,
        0,
        "",
        "",
        "",
        "",
        "",
        1
      ]
    },
    {
      "id": 2800302,
      "leagueId": 11,
      "leagueColor": "#663333",
      "playtime": "2026/05/03 23:00",
      "leagueName": "法甲",
      "homeName": "南特",
      "homeId": 263,
      "awayName": "马赛",
      "awayId": 211,
      "fullscore": "",
      "halfscore": "",
      "result": "",
      "raw": [
        2800302,
        11,
        "#663333",
        "2026/05/03 23:00",
        263,
        211,
        "",
        "",
        "法甲",
        "法甲",
        "FRA D1",
        "南特",
        "南特",
        "Nantes",
        "马赛",
        "馬賽",
        "Marseille",
        0,
        0,
        "",
        "",
        "",
        "",
        "",
        1
      ]
    },
    {
      "id": 2800294,
      "leagueId": 11,
      "leagueColor": "#663333",
      "playtime": "2026/04/26 23:00",
      "leagueName": "法甲",
      "homeName": "马赛",
      "homeId": 211,
      "awayName": "尼斯",
      "awayId": 259,
      "fullscore": "",
      "halfscore": "",
      "result": "",
      "raw": [
        2800294,
        11,
        "#663333",
        "2026/04/26 23:00",
        211,
        259,
        "",
        "",
        "法甲",
        "法甲",
        "FRA D1",
        "马赛",
        "馬賽",
        "Marseille",
        "尼斯",
        "奈斯",
        "Nice",
        0,
        0,
        "",
        "",
        "",
        "",
        "",
        1
      ]
    },
    {
      "id": 2800283,
      "leagueId": 11,
      "leagueColor": "#663333",
      "playtime": "2026/04/19 23:00",
      "leagueName": "法甲",
      "homeName": "洛里昂",
      "homeId": 333,
      "awayName": "马赛",
      "awayId": 211,
      "fullscore": "",
      "halfscore": "",
      "result": "",
      "raw": [
        2800283,
        11,
        "#663333",
        "2026/04/19 23:00",
        333,
        211,
        "",
        "",
        "法甲",
        "法甲",
        "FRA D1",
        "洛里昂",
        "羅連安特",
        "Lorient",
        "马赛",
        "馬賽",
        "Marseille",
        0,
        0,
        "",
        "",
        "",
        "",
        "",
        1
      ]
    },
    {
      "id": 2800275,
      "leagueId": 11,
      "leagueColor": "#663333",
      "playtime": "2026/04/12 23:00",
      "leagueName": "法甲",
      "homeName": "马赛",
      "homeId": 211,
      "awayName": "梅斯",
      "awayId": 214,
      "fullscore": "",
      "halfscore": "",
      "result": "",
      "raw": [
        2800275,
        11,
        "#663333",
        "2026/04/12 23:00",
        211,
        214,
        "",
        "",
        "法甲",
        "法甲",
        "FRA D1",
        "马赛",
        "馬賽",
        "Marseille",
        "梅斯",
        "梅斯",
        "Metz",
        0,
        0,
        "",
        "",
        "",
        "",
        "",
        1
      ]
    },
    {
      "id": 2800268,
      "leagueId": 11,
      "leagueColor": "#663333",
      "playtime": "2026/04/05 23:00",
      "leagueName": "法甲",
      "homeName": "摩纳哥",
      "homeId": 197,
      "awayName": "马赛",
      "awayId": 211,
      "fullscore": "",
      "halfscore": "",
      "result": "",
      "raw": [
        2800268,
        11,
        "#663333",
        "2026/04/05 23:00",
        197,
        211,
        "",
        "",
        "法甲",
        "法甲",
        "FRA D1",
        "摩纳哥",
        "摩納哥",
        "Monaco",
        "马赛",
        "馬賽",
        "Marseille",
        0,
        0,
        "",
        "",
        "",
        "",
        "",
        1
      ]
    },
    {
      "id": 2800256,
      "leagueId": 11,
      "leagueColor": "#663333",
      "playtime": "2026/03/23 00:00",
      "leagueName": "法甲",
      "homeName": "马赛",
      "homeId": 211,
      "awayName": "里尔",
      "awayId": 266,
      "fullscore": "",
      "halfscore": "",
      "result": "",
      "raw": [
        2800256,
        11,
        "#663333",
        "2026/03/23 00:00",
        211,
        266,
        "",
        "",
        "法甲",
        "法甲",
        "FRA D1",
        "马赛",
        "馬賽",
        "Marseille",
        "里尔",
        "利爾",
        "Lille",
        0,
        0,
        "",
        "",
        "",
        "",
        "",
        1
      ]
    },
    {
      "id": 2800247,
      "leagueId": 11,
      "leagueColor": "#663333",
      "playtime": "2026/03/16 00:00",
      "leagueName": "法甲",
      "homeName": "马赛",
      "homeId": 211,
      "awayName": "欧塞尔",
      "awayId": 215,
      "fullscore": "",
      "halfscore": "",
      "result": "",
      "raw": [
        2800247,
        11,
        "#663333",
        "2026/03/16 00:00",
        211,
        215,
        "",
        "",
        "法甲",
        "法甲",
        "FRA D1",
        "马赛",
        "馬賽",
        "Marseille",
        "欧塞尔",
        "歐塞爾",
        "AJ Auxerre",
        0,
        0,
        "",
        "",
        "",
        "",
        "",
        1
      ]
    },
    {
      "id": 2800243,
      "leagueId": 11,
      "leagueColor": "#663333",
      "playtime": "2026/03/09 00:00",
      "leagueName": "法甲",
      "homeName": "图卢兹",
      "homeId": 216,
      "awayName": "马赛",
      "awayId": 211,
      "fullscore": "",
      "halfscore": "",
      "result": "",
      "raw": [
        2800243,
        11,
        "#663333",
        "2026/03/09 00:00",
        216,
        211,
        "",
        "",
        "法甲",
        "法甲",
        "FRA D1",
        "图卢兹",
        "圖魯茲",
        "Toulouse",
        "马赛",
        "馬賽",
        "Marseille",
        0,
        0,
        "",
        "",
        "",
        "",
        "",
        1
      ]
    },
    {
      "id": 2800229,
      "leagueId": 11,
      "leagueColor": "#663333",
      "playtime": "2026/03/02 00:00",
      "leagueName": "法甲",
      "homeName": "马赛",
      "homeId": 211,
      "awayName": "里昂",
      "awayId": 205,
      "fullscore": "",
      "halfscore": "",
      "result": "",
      "raw": [
        2800229,
        11,
        "#663333",
        "2026/03/02 00:00",
        211,
        205,
        "",
        "",
        "法甲",
        "法甲",
        "FRA D1",
        "马赛",
        "馬賽",
        "Marseille",
        "里昂",
        "里昂",
        "Lyon",
        0,
        0,
        "",
        "",
        "",
        "",
        "",
        1
      ]
    },
    {
      "id": 2800219,
      "leagueId": 11,
      "leagueColor": "#663333",
      "playtime": "2026/02/23 00:00",
      "leagueName": "法甲",
      "homeName": "布雷斯特",
      "homeId": 306,
      "awayName": "马赛",
      "awayId": 211,
      "fullscore": "",
      "halfscore": "",
      "result": "",
      "raw": [
        2800219,
        11,
        "#663333",
        "2026/02/23 00:00",
        306,
        211,
        "",
        "",
        "法甲",
        "法甲",
        "FRA D1",
        "布雷斯特",
        "比斯特",
        "Stade Brestois",
        "马赛",
        "馬賽",
        "Marseille",
        0,
        0,
        "",
        "",
        "",
        "",
        "",
        1
      ]
    },
    {
      "id": 2800212,
      "leagueId": 11,
      "leagueColor": "#663333",
      "playtime": "2026/02/16 00:00",
      "leagueName": "法甲",
      "homeName": "马赛",
      "homeId": 211,
      "awayName": "斯特拉斯堡",
      "awayId": 260,
      "fullscore": "",
      "halfscore": "",
      "result": "",
      "raw": [
        2800212,
        11,
        "#663333",
        "2026/02/16 00:00",
        211,
        260,
        "",
        "",
        "法甲",
        "法甲",
        "FRA D1",
        "马赛",
        "馬賽",
        "Marseille",
        "斯特拉斯堡",
        "史特拉斯堡",
        "Strasbourg",
        0,
        0,
        "",
        "",
        "",
        "",
        "",
        1
      ]
    },
    {
      "id": 2800207,
      "leagueId": 11,
      "leagueColor": "#663333",
      "playtime": "2026/02/09 00:00",
      "leagueName": "法甲",
      "homeName": "巴黎圣日耳曼",
      "homeId": 271,
      "awayName": "马赛",
      "awayId": 211,
      "fullscore": "",
      "halfscore": "",
      "result": "",
      "raw": [
        2800207,
        11,
        "#663333",
        "2026/02/09 00:00",
        271,
        211,
        "",
        "",
        "法甲",
        "法甲",
        "FRA D1",
        "巴黎圣日耳曼",
        "巴黎聖日門",
        "Paris Saint Germain (PSG)",
        "马赛",
        "馬賽",
        "Marseille",
        0,
        0,
        "",
        "",
        "",
        "",
        "",
        1
      ]
    },
    {
      "id": 2800196,
      "leagueId": 11,
      "leagueColor": "#663333",
      "playtime": "2026/02/02 00:00",
      "leagueName": "法甲",
      "homeName": "巴黎足球会",
      "homeId": 1796,
      "awayName": "马赛",
      "awayId": 211,
      "fullscore": "",
      "halfscore": "",
      "result": "",
      "raw": [
        2800196,
        11,
        "#663333",
        "2026/02/02 00:00",
        1796,
        211,
        "",
        "",
        "法甲",
        "法甲",
        "FRA D1",
        "巴黎足球会",
        "巴黎FC",
        "Paris FC",
        "马赛",
        "馬賽",
        "Marseille",
        0,
        0,
        "",
        "",
        "",
        "",
        "",
        1
      ]
    },
    {
      "id": 2861171,
      "leagueId": 103,
      "leagueColor": "#f75000",
      "playtime": "2026/01/29 04:00",
      "leagueName": "欧冠杯",
      "homeName": "布鲁日",
      "homeId": 148,
      "awayName": "马赛",
      "awayId": 211,
      "fullscore": "",
      "halfscore": "",
      "result": "",
      "raw": [
        2861171,
        103,
        "#f75000",
        "2026/01/29 04:00",
        148,
        211,
        "",
        "",
        "欧冠杯",
        "歐冠盃",
        "UEFA CL",
        "布鲁日",
        "布魯日",
        "Club Brugge",
        "马赛",
        "馬賽",
        "Marseille",
        0,
        0,
        "",
        "",
        "",
        "",
        "",
        1
      ]
    },
    {
      "id": 2800185,
      "leagueId": 11,
      "leagueColor": "#663333",
      "playtime": "2026/01/25 04:05",
      "leagueName": "法甲",
      "homeName": "马赛",
      "homeId": 211,
      "awayName": "朗斯",
      "awayId": 202,
      "fullscore": "",
      "halfscore": "",
      "result": "",
      "raw": [
        2800185,
        11,
        "#663333",
        "2026/01/25 04:05",
        211,
        202,
        "",
        "",
        "法甲",
        "法甲",
        "FRA D1",
        "马赛",
        "馬賽",
        "Marseille",
        "朗斯",
        "朗斯",
        "Lens",
        0,
        0,
        "",
        "",
        "",
        "",
        "",
        1
      ]
    },
    {
      "id": 2861103,
      "leagueId": 103,
      "leagueColor": "#f75000",
      "playtime": "2026/01/22 04:00",
      "leagueName": "欧冠杯",
      "homeName": "马赛",
      "homeId": 211,
      "awayName": "利物浦",
      "awayId": 25,
      "fullscore": "",
      "halfscore": "",
      "result": "",
      "raw": [
        2861103,
        103,
        "#f75000",
        "2026/01/22 04:00",
        211,
        25,
        "",
        "",
        "欧冠杯",
        "歐冠盃",
        "UEFA CL",
        "马赛",
        "馬賽",
        "Marseille",
        "利物浦",
        "利物浦",
        "Liverpool",
        0,
        0,
        "",
        "",
        "",
        "",
        "",
        1
      ]
    },
    {
      "id": 2800172,
      "leagueId": 11,
      "leagueColor": "#663333",
      "playtime": "2026/01/18 04:05",
      "leagueName": "法甲",
      "homeName": "昂热",
      "homeId": 304,
      "awayName": "马赛",
      "awayId": 211,
      "fullscore": "",
      "halfscore": "",
      "result": "",
      "raw": [
        2800172,
        11,
        "#663333",
        "2026/01/18 04:05",
        304,
        211,
        "",
        "",
        "法甲",
        "法甲",
        "FRA D1",
        "昂热",
        "昂熱",
        "Angers",
        "马赛",
        "馬賽",
        "Marseille",
        0,
        0,
        "",
        "",
        "",
        "",
        "",
        1
      ]
    },
    {
      "id": 2800167,
      "leagueId": 11,
      "leagueColor": "#663333",
      "playtime": "2026/01/04 22:00",
      "leagueName": "法甲",
      "homeName": "马赛",
      "homeId": 211,
      "awayName": "南特",
      "awayId": 263,
      "fullscore": "",
      "halfscore": "",
      "result": "",
      "raw": [
        2800167,
        11,
        "#663333",
        "2026/01/04 22:00",
        211,
        263,
        "",
        "",
        "法甲",
        "法甲",
        "FRA D1",
        "马赛",
        "馬賽",
        "Marseille",
        "南特",
        "南特",
        "Nantes",
        0,
        0,
        "",
        "",
        "",
        "",
        "",
        1
      ]
    },
    {
      "id": 2905767,
      "leagueId": 54,
      "leagueColor": "#297CA5",
      "playtime": "2025/12/20 21:00",
      "leagueName": "法国杯",
      "homeName": "马赛",
      "homeId": 211,
      "awayName": "普瑞兰斯",
      "awayId": 7052,
      "fullscore": "",
      "halfscore": "",
      "result": "",
      "raw": [
        2905767,
        54,
        "#297CA5",
        "2025/12/20 21:00",
        211,
        7052,
        "",
        "",
        "法国杯",
        "法國盃",
        "FRAC",
        "马赛",
        "馬賽",
        "Marseille",
        "普瑞兰斯",
        "布爾格",
        "Bourg Peronnas",
        0,
        0,
        "",
        "",
        "",
        "",
        "",
        1
      ]
    },
    {
      "id": 2800158,
      "leagueId": 11,
      "leagueColor": "#663333",
      "playtime": "2025/12/15 03:45",
      "leagueName": "法甲",
      "homeName": "马赛",
      "homeId": 211,
      "awayName": "摩纳哥",
      "awayId": 197,
      "fullscore": "",
      "halfscore": "",
      "result": "",
      "raw": [
        2800158,
        11,
        "#663333",
        "2025/12/15 03:45",
        211,
        197,
        "",
        "",
        "法甲",
        "法甲",
        "FRA D1",
        "马赛",
        "馬賽",
        "Marseille",
        "摩纳哥",
        "摩納哥",
        "Monaco",
        0,
        0,
        "",
        "",
        "",
        "",
        "",
        1
      ]
    },
    {
      "id": 2861201,
      "leagueId": 103,
      "leagueColor": "#f75000",
      "playtime": "2025/12/10 04:00",
      "leagueName": "欧冠杯",
      "homeName": "圣吉罗斯",
      "homeId": 1317,
      "awayName": "马赛",
      "awayId": 211,
      "fullscore": "2-3",
      "halfscore": "1-2",
      "result": "胜",
      "raw": [
        2861201,
        103,
        "#f75000",
        "2025/12/10 04:00",
        1317,
        211,
        "2-3",
        "1-2",
        "欧冠杯",
        "歐冠盃",
        "UEFA CL",
        "圣吉罗斯",
        "聖吉羅斯",
        "Saint Gilloise",
        "马赛",
        "馬賽",
        "Marseille",
        0,
        0,
        "",
        "受让平手/半球|-0/-0.5",
        "赢",
        "大",
        "胜",
        1
      ]
    },
    {
      "id": 2800148,
      "leagueId": 11,
      "leagueColor": "#663333",
      "playtime": "2025/12/06 04:00",
      "leagueName": "法甲",
      "homeName": "里尔",
      "homeId": 266,
      "awayName": "马赛",
      "awayId": 211,
      "fullscore": "1-0",
      "halfscore": "1-0",
      "result": "负",
      "raw": [
        2800148,
        11,
        "#663333",
        "2025/12/06 04:00",
        266,
        211,
        "1-0",
        "1-0",
        "法甲",
        "法甲",
        "FRA D1",
        "里尔",
        "利爾",
        "Lille",
        "马赛",
        "馬賽",
        "Marseille",
        0,
        0,
        "",
        "平手/半球|0/0.5",
        "输",
        "小",
        "负",
        1
      ]
    },
    {
      "id": 2800140,
      "leagueId": 11,
      "leagueColor": "#663333",
      "playtime": "2025/11/30 04:05",
      "leagueName": "法甲",
      "homeName": "马赛",
      "homeId": 211,
      "awayName": "图卢兹",
      "awayId": 216,
      "fullscore": "2-2",
      "halfscore": "0-1",
      "result": "平",
      "raw": [
        2800140,
        11,
        "#663333",
        "2025/11/30 04:05",
        211,
        216,
        "2-2",
        "0-1",
        "法甲",
        "法甲",
        "FRA D1",
        "马赛",
        "馬賽",
        "Marseille",
        "图卢兹",
        "圖魯茲",
        "Toulouse",
        0,
        0,
        "",
        "半球/一球|0.5/1",
        "输",
        "大",
        "平",
        1
      ]
    }
  ]
}